src/__init__.py
src/cli.py
src/hmh_exception.py
src/commands/__init__.py
src/commands/init.py
src/commands/run.py
src/commands/serve.py
src/commands/workflow.py
src/components/__init__.py
src/components/database.py
src/components/rest.py
harmonyhub_cli-0.0.9.dist-info/METADATA
harmonyhub_cli-0.0.9.dist-info/WHEEL
harmonyhub_cli-0.0.9.dist-info/entry_points.txt
harmonyhub_cli-0.0.9.dist-info/top_level.txt
harmonyhub_cli-0.0.9.dist-info/RECORD
