Metadata-Version: 2.1
Name: harmonyhub-cli
Version: 0.0.9
Summary: A CLI library for HarmonyHub
Home-page: https://github.com/rahgadda/HarmonyHub
Author: Rahul Kiran Gaddam
Author-email: gaddam.rahul@gmail.com
Classifier: Programming Language :: Python :: 3
Classifier: License :: OSI Approved :: MIT License
Classifier: Operating System :: OS Independent
Requires-Python: >=3.6
Requires-Dist: jq==1.8.0
Requires-Dist: PyYAML==6.0.2
Requires-Dist: jinja2==3.1.4
Requires-Dist: fastapi==0.115.5
Requires-Dist: uvicorn==0.22.0
Requires-Dist: sqlalchemy==2.0.36
Requires-Dist: pandas==2.2.3
